irc3/__init__.py
irc3/__main__.py
irc3/_gen_doc.py
irc3/_parse_rfc.py
irc3/_rfc.py
irc3/asynchronous.py
irc3/base.py
irc3/compat.py
irc3/config.py
irc3/dec.py
irc3/rfc.py
irc3/rfc1459.txt
irc3/rfc2812.txt
irc3/tags.py
irc3/testing.py
irc3/utils.py
irc3/dcc/__init__.py
irc3/dcc/client.py
irc3/dcc/manager.py
irc3/plugins/__init__.py
irc3/plugins/asynchronious.py
irc3/plugins/autocommand.py
irc3/plugins/autojoins.py
irc3/plugins/casefold.py
irc3/plugins/command.py
irc3/plugins/core.py
irc3/plugins/cron.py
irc3/plugins/ctcp.py
irc3/plugins/dcc.py
irc3/plugins/feeds.py
irc3/plugins/fifo.py
irc3/plugins/human.py
irc3/plugins/log.py
irc3/plugins/logger.py
irc3/plugins/pager.py
irc3/plugins/quakenet.py
irc3/plugins/sasl.py
irc3/plugins/search.py
irc3/plugins/shell_command.py
irc3/plugins/slack.py
irc3/plugins/social.py
irc3/plugins/storage.py
irc3/plugins/uptime.py
irc3/plugins/userlist.py
irc3/plugins/web.py
irc3/template/__init__.py
irc3/template/__main__.py
irc3/template/config.ini
irc3/template/plugin.py
irc3d/__init__.py
irc3d/__main__.py
irc3d/dec.py
irc3d/motd.txt
irc3d/plugins/__init__.py
irc3d/plugins/command.py
irc3d/plugins/core.py
irc3d/plugins/userlist.py
irc3-1.1.10.dist-info/LICENSE
irc3-1.1.10.dist-info/METADATA
irc3-1.1.10.dist-info/WHEEL
irc3-1.1.10.dist-info/entry_points.txt
irc3-1.1.10.dist-info/top_level.txt
irc3-1.1.10.dist-info/RECORD
