Metadata-Version: 2.1
Name: irc3
Version: 1.1.10
Summary: plugable irc client library based on asyncio with DCC and SASL support
Home-page: https://github.com/gawel/irc3/
Author: Gael Pasgrimaud
Author-email: gael@gawel.org
License: MIT
Keywords: irc dcc asyncio
Platform: UNKNOWN
Classifier: Intended Audience :: Developers
Classifier: Programming Language :: Python :: 3.7
Classifier: Programming Language :: Python :: 3.9
Classifier: Programming Language :: Python :: 3.10
Classifier: Programming Language :: Python :: 3.11
Classifier: License :: OSI Approved :: MIT License
Classifier: Topic :: Communications :: Chat :: Internet Relay Chat
Classifier: Development Status :: 5 - Production/Stable
Provides-Extra: test
Provides-Extra: web
License-File: LICENSE
